rsc_py/__init__.py
rsc_py-0.1.0.dist-info/LICENSE
rsc_py-0.1.0.dist-info/METADATA
rsc_py-0.1.0.dist-info/WHEEL
rsc_py-0.1.0.dist-info/top_level.txt
rsc_py-0.1.0.dist-info/RECORD
