Metadata-Version: 2.1
Name: rsc-py
Version: 0.1.0
Summary: A library for controlling PowerPoint via Remote Show Control using Python
Home-page: https://github.com/deffuseyou/rsc_py
Author: deffuseyou
Author-email: kriulindmitry@mail.ru
Classifier: Programming Language :: Python :: 3
Classifier: License :: OSI Approved :: MIT License
Classifier: Operating System :: OS Independent
Requires-Python: >=3.6
License-File: LICENSE
